pycbsdk/__init__.py
pycbsdk/__version__.py
pycbsdk/cbsdk.py
pycbsdk/cbhw/__init__.py
pycbsdk/cbhw/config.py
pycbsdk/cbhw/consts.py
pycbsdk/cbhw/handler.py
pycbsdk/cbhw/params.py
pycbsdk/cbhw/device/__init__.py
pycbsdk/cbhw/device/base.py
pycbsdk/cbhw/device/nsp.py
pycbsdk/cbhw/io/__init__.py
pycbsdk/cbhw/io/base.py
pycbsdk/cbhw/io/datagram.py
pycbsdk/cbhw/packet/__init__.py
pycbsdk/cbhw/packet/abstract.py
pycbsdk/cbhw/packet/common.py
pycbsdk/cbhw/packet/factory.py
pycbsdk/cbhw/packet/packets.py
pycbsdk/cbhw/packet/v311.py
pycbsdk/cbhw/packet/v40.py
pycbsdk/cbhw/packet/v41.py
pycbsdk/cbhw/packet/v42.py
pycbsdk/cbhw/packet/header/__init__.py
pycbsdk/cbhw/packet/header/v311.py
pycbsdk/cbhw/packet/header/v40.py
pycbsdk/cbhw/packet/header/v41.py
pycbsdk/examples/__init__.py
pycbsdk/examples/comments.py
pycbsdk/examples/group_sample_intervals.py
pycbsdk/examples/print_rates.py
pycbsdk/misc/__init__.py
pycbsdk/misc/net.py
pycbsdk-0.4.0.dist-info/METADATA
pycbsdk-0.4.0.dist-info/WHEEL
pycbsdk-0.4.0.dist-info/entry_points.txt
pycbsdk-0.4.0.dist-info/licenses/LICENSE
pycbsdk-0.4.0.dist-info/RECORD
