Metadata-Version: 2.4
Name: pycbsdk
Version: 0.4.0
Summary: Pure Python interface to Blackrock Neurotech Cerebus devices
Author-email: Chadwick Boulay <chadwick.boulay@gmail.com>
License-Expression: MIT
License-File: LICENSE
Requires-Python: >=3.10
Requires-Dist: aenum>=3.1.15
Requires-Dist: ifaddr>=0.2.0
Requires-Dist: numpy
Provides-Extra: test
Requires-Dist: pytest>=8.3.3; extra == 'test'
